{
  "codeName" : "usr0318595478",
  "controlType" : "PANEL",
  "dynaModelFilePath" : "PSSYSAPPS/crmweb/PSAPPDATAENTITIES/account/PSPANELS/usr0318595478.json",
  "layoutMode" : "TABLE_24COL",
  "logicName" : "List_列表项面板",
  "memo" : "自动生成",
  "getPSAppDataEntity" : {
    "modelref" : true,
    "path" : "PSSYSAPPS/crmweb/PSAPPDATAENTITIES/account.json"
  },
  "getPSLayout" : {
    "childColMD" : 24,
    "columnCount" : 24,
    "layout" : "TABLE_24COL"
  },
  "modelid" : "f4943070acaabe416fb45692d98e9c10",
  "modeltype" : "PSSYSVIEWPANEL"
}